{"type":"FeatureCollection", "features": [
{"type":"Feature","geometry":{"type":"Point","coordinates":[-102.074755,19.406355,0]},"properties":{"name":"19.406351, -102.074752","styleUrl":"#icon-1899-DB4436-nodesc","icon-opacity":1,"icon-color":"#db4436","icon-scale":1,"icon-offset":[32,64],"icon-offset-units":["pixels","insetPixels"],"icon":"https://www.gstatic.com/mapspro/images/stock/503-wht-blank_maps.png"}},
{"type":"Feature","geometry":{"type":"Point","coordinates":[-102.033198,19.427041,0]},"properties":{"name":"Hermanos López Rayon 176, Periodista, 60110 Uruapan, Mich.","styleUrl":"#icon-1899-DB4436-nodesc","icon-opacity":1,"icon-color":"#db4436","icon-scale":1,"icon-offset":[32,64],"icon-offset-units":["pixels","insetPixels"],"icon":"https://www.gstatic.com/mapspro/images/stock/503-wht-blank_maps.png"}},
{"type":"Feature","geometry":{"type":"Point","coordinates":[-102.033198,19.427041,0]},"properties":{"name":"Hermanos López Rayon 176, Periodista, 60110 Uruapan, Mich.","styleUrl":"#icon-1899-DB4436-nodesc","icon-opacity":1,"icon-color":"#db4436","icon-scale":1,"icon-offset":[32,64],"icon-offset-units":["pixels","insetPixels"],"icon":"https://www.gstatic.com/mapspro/images/stock/503-wht-blank_maps.png"}},
{"type":"Feature","geometry":{"type":"Point","coordinates":[-102.074761,19.406351,0]},"properties":{"name":"19.406351, -102.074752","styleUrl":"#icon-1899-DB4436-nodesc","icon-opacity":1,"icon-color":"#db4436","icon-scale":1,"icon-offset":[32,64],"icon-offset-units":["pixels","insetPixels"],"icon":"https://www.gstatic.com/mapspro/images/stock/503-wht-blank_maps.png"}}
]}